pdcrier/__init__.py
pdcrier/cli/__init__.py
pdcrier/cli/alerts.py
pdcrier/pagerduty.py
pdcrier/utils.py
pdcrier-0.2.0.dist-info/entry_points.txt
pdcrier-0.2.0.dist-info/LICENSE
pdcrier-0.2.0.dist-info/WHEEL
pdcrier-0.2.0.dist-info/METADATA
pdcrier-0.2.0.dist-info/RECORD
