Metadata-Version: 2.1
Name: pdcrier
Version: 0.2.0
Summary: Wrapper scripts for creating PagerDuty alerts
Home-page: https://github.com/unixorn/pdcrier
License: Apache 2.0
Author: Joe Block
Author-email: jpb@unixorn.net
Requires-Python: >=3.9,<4.0
Classifier: License :: Other/Proprietary License
Classifier: Programming Language :: Python :: 3
Classifier: Programming Language :: Python :: 3.10
Classifier: Programming Language :: Python :: 3.9
Requires-Dist: pdpyras (>=4.4.0,<5.0.0)
Requires-Dist: pyaml (>=21.10.1,<22.0.0)
Project-URL: Bug Tracker, https://github.com/unixorn/pdcrier/issues
Project-URL: Repository, https://github.com/unixorn/pdcrier
